Metadata-Version: 1.0
Name: dly-distributions
Version: 1.0
Summary: Gaussian/Binomial distributions
Home-page: UNKNOWN
Author: Derek Ly
Author-email: UNKNOWN
License: UNKNOWN
Platform: UNKNOWN
